aliyunsdkeventbridge/__init__.py
aliyunsdkeventbridge/request/__init__.py
aliyunsdkeventbridge/request/v20200401/CreateApiDestinationRequest.py
aliyunsdkeventbridge/request/v20200401/CreateConnectionRequest.py
aliyunsdkeventbridge/request/v20200401/CreateEventBusRequest.py
aliyunsdkeventbridge/request/v20200401/CreateEventSourceRequest.py
aliyunsdkeventbridge/request/v20200401/CreateEventStreamingRequest.py
aliyunsdkeventbridge/request/v20200401/CreateRuleRequest.py
aliyunsdkeventbridge/request/v20200401/CreateServiceLinkedRoleForProductRequest.py
aliyunsdkeventbridge/request/v20200401/DeleteApiDestinationRequest.py
aliyunsdkeventbridge/request/v20200401/DeleteConnectionRequest.py
aliyunsdkeventbridge/request/v20200401/DeleteEventBusRequest.py
aliyunsdkeventbridge/request/v20200401/DeleteEventSourceRequest.py
aliyunsdkeventbridge/request/v20200401/DeleteEventStreamingRequest.py
aliyunsdkeventbridge/request/v20200401/DeleteRuleRequest.py
aliyunsdkeventbridge/request/v20200401/DeleteTargetsRequest.py
aliyunsdkeventbridge/request/v20200401/DisableRuleRequest.py
aliyunsdkeventbridge/request/v20200401/EnableRuleRequest.py
aliyunsdkeventbridge/request/v20200401/GetApiDestinationRequest.py
aliyunsdkeventbridge/request/v20200401/GetConnectionRequest.py
aliyunsdkeventbridge/request/v20200401/GetEventBusRequest.py
aliyunsdkeventbridge/request/v20200401/GetEventStreamingRequest.py
aliyunsdkeventbridge/request/v20200401/GetRuleRequest.py
aliyunsdkeventbridge/request/v20200401/ListAliyunOfficialEventSourcesRequest.py
aliyunsdkeventbridge/request/v20200401/ListApiDestinationsRequest.py
aliyunsdkeventbridge/request/v20200401/ListConnectionsRequest.py
aliyunsdkeventbridge/request/v20200401/ListEventBusesRequest.py
aliyunsdkeventbridge/request/v20200401/ListEventStreamingsRequest.py
aliyunsdkeventbridge/request/v20200401/ListRulesRequest.py
aliyunsdkeventbridge/request/v20200401/ListTargetsRequest.py
aliyunsdkeventbridge/request/v20200401/ListUserDefinedEventSourcesRequest.py
aliyun_python_sdk_eventbridge-1.0.14.dist-info/LICENSE
aliyun_python_sdk_eventbridge-1.0.14.dist-info/METADATA
aliyun_python_sdk_eventbridge-1.0.14.dist-info/WHEEL
aliyun_python_sdk_eventbridge-1.0.14.dist-info/top_level.txt
aliyun_python_sdk_eventbridge-1.0.14.dist-info/RECORD
